sightseer/__init__.py
sightseer/blocks.py
sightseer/proc.py
sightseer/sightseer.py
sightseer/zoo.py
sightseer-1.1.3.dist-info/LICENSE
sightseer-1.1.3.dist-info/METADATA
sightseer-1.1.3.dist-info/WHEEL
sightseer-1.1.3.dist-info/top_level.txt
sightseer-1.1.3.dist-info/RECORD
