Metadata-Version: 2.1
Name: sightseer
Version: 1.1.3
Summary: State-of-the-art Computer Vision and Object Detection for TensorFlow.
Home-page: https://github.com/rish-16/sight
Author: Rishabh Anand
Author-email: mail.rishabh.anand@gmail.com
License: ASF
Download-URL: https://github.com/rish-16/sight/archive/1.0.0.tar.gz
Platform: UNKNOWN
